<?xml version="1.0" encoding="UTF-8"?>
<!DOCTYPE mapper PUBLIC "-//mybatis.org//DTD Mapper 3.0//EN" "http://mybatis.org/dtd/mybatis-3-mapper.dtd">
<mapper namespace="com.beiyelin.service.footstone.dao.TestUserMapper">
  <resultMap id="BaseResultMap" type="com.beiyelin.service.footstone.model.TestUser">
    <!--
      WARNING - @mbggenerated
      This element is automatically generated by MyBatis Generator, do not modify.
      This element was generated on Sat Oct 01 16:27:39 CST 2016.
    -->
    <id column="user_id" jdbcType="CHAR" property="userId" />
    <result column="user_name" jdbcType="VARCHAR" property="userName" />
    <result column="user_birthday" jdbcType="DATE" property="userBirthday" />
    <result column="user_salary" jdbcType="DOUBLE" property="userSalary" />
  </resultMap>
  <delete id="deleteByPrimaryKey" parameterType="java.lang.String">
    <!--
      WARNING - @mbggenerated
      This element is automatically generated by MyBatis Generator, do not modify.
      This element was generated on Sat Oct 01 16:27:39 CST 2016.
    -->
    delete from user
    where user_id = #{userId,jdbcType=CHAR}
  </delete>
  <insert id="insert" parameterType="com.beiyelin.service.footstone.model.TestUser">
    <!--
      WARNING - @mbggenerated
      This element is automatically generated by MyBatis Generator, do not modify.
      This element was generated on Sat Oct 01 16:27:39 CST 2016.
    -->
    insert into user (user_id, user_name, user_birthday, 
      user_salary)
    values (#{userId,jdbcType=CHAR}, #{userName,jdbcType=VARCHAR}, #{userBirthday,jdbcType=DATE}, 
      #{userSalary,jdbcType=DOUBLE})
  </insert>
  <update id="updateByPrimaryKey" parameterType="com.beiyelin.service.footstone.model.TestUser">
    <!--
      WARNING - @mbggenerated
      This element is automatically generated by MyBatis Generator, do not modify.
      This element was generated on Sat Oct 01 16:27:39 CST 2016.
    -->
    update user
    set user_name = #{userName,jdbcType=VARCHAR},
      user_birthday = #{userBirthday,jdbcType=DATE},
      user_salary = #{userSalary,jdbcType=DOUBLE}
    where user_id = #{userId,jdbcType=CHAR}
  </update>
  <select id="selectByPrimaryKey" parameterType="java.lang.String" resultMap="BaseResultMap">
    <!--
      WARNING - @mbggenerated
      This element is automatically generated by MyBatis Generator, do not modify.
      This element was generated on Sat Oct 01 16:27:39 CST 2016.
    -->
    select user_id, user_name, user_birthday, user_salary
    from user
    where user_id = #{userId,jdbcType=CHAR}
  </select>
  <select id="selectAll" resultMap="BaseResultMap">
    <!--
      WARNING - @mbggenerated
      This element is automatically generated by MyBatis Generator, do not modify.
      This element was generated on Sat Oct 01 16:27:39 CST 2016.
    -->
    select user_id, user_name, user_birthday, user_salary
    from user
  </select>
</mapper>